shs_mcp_demo/__init__.py
shs_mcp_demo-0.1.0.dist-info/METADATA
shs_mcp_demo-0.1.0.dist-info/WHEEL
shs_mcp_demo-0.1.0.dist-info/entry_points.txt
shs_mcp_demo-0.1.0.dist-info/RECORD
